{
  "idEvent": "602129",
  "idSoccerXML": "401980",
  "strEvent": "Liverpool vs Norwich",
  "strFilename": "English Premier League 2019-08-09 Liverpool vs Norwich",
  "strSport": "Soccer",
  "idLeague": "4328",
  "strLeague": "English Premier League",
  "strSeason": "1920",
  "strDescriptionEN": null,
  "strHomeTeam": "Liverpool",
  "strAwayTeam": "Norwich",
  "intHomeScore": null,
  "intRound": "1",
  "intAwayScore": null,
  "intSpectators": null,
  "strHomeGoalDetails": null,
  "strHomeRedCards": null,
  "strHomeYellowCards": null,
  "strHomeLineupGoalkeeper": null,
  "strHomeLineupDefense": null,
  "strHomeLineupMidfield": null,
  "strHomeLineupForward": null,
  "strHomeLineupSubstitutes": null,
  "strHomeFormation": null,
  "strAwayRedCards": null,
  "strAwayYellowCards": null,
  "strAwayGoalDetails": null,
  "strAwayLineupGoalkeeper": null,
  "strAwayLineupDefense": null,
  "strAwayLineupMidfield": null,
  "strAwayLineupForward": null,
  "strAwayLineupSubstitutes": null,
  "strAwayFormation": null,
  "intHomeShots": null,
  "intAwayShots": null,
  "dateEvent": "2019-08-09",
  "datetimeEventUTC": null,
  "strDate": "09/08/19",
  "strTime": "19:00:00+00:00",
  "strTVStation": null,
  "idHomeTeam": "133602",
  "idAwayTeam": "133608",
  "strResult": null,
  "strCircuit": null,
  "strCountry": null,
  "strCity": null,
  "strPoster": null,
  "strFanart": null,
  "strThumb": null,
  "strBanner": null,
  "strMap": null,
  "strTweet1": null,
  "strTweet2": null,
  "strTweet3": null,
  "strVideo": null,
  "strLocked": "unlocked"
  }